example/__init__.py
example/authorize_driver.py
example/authorize_rider.py
example/driver_dashboard.py
example/request_ride.py
example/rider_dashboard.py
example/utils.py
tests/__init__.py
tests/test_auth.py
tests/test_client.py
tests/test_errors.py
tests/test_request_utils.py
tests/test_session.py
tests/vcr_config.py
uber_rides/__init__.py
uber_rides/auth.py
uber_rides/client.py
uber_rides/errors.py
uber_rides/request.py
uber_rides/session.py
uber_rides/utils/__init__.py
uber_rides/utils/auth.py
uber_rides/utils/handlers.py
uber_rides/utils/http.py
uber_rides/utils/request.py
uber_rides-0.6.0.dist-info/DESCRIPTION.rst
uber_rides-0.6.0.dist-info/METADATA
uber_rides-0.6.0.dist-info/RECORD
uber_rides-0.6.0.dist-info/WHEEL
uber_rides-0.6.0.dist-info/metadata.json
uber_rides-0.6.0.dist-info/top_level.txt
