Metadata-Version: 1.0
Name: uber_rides
Version: 0.6.0
Summary: Official Uber API Python SDK
Home-page: https://github.com/uber/rides-python-sdk
Author: Uber Technologies, Inc.
Author-email: dev-advocates@uber.com
License: MIT
Keywords: uber,api,sdk,rides,library
Platform: UNKNOWN
